{
  "luis_schema_version": "3.1.0",
  "versionId": "Dispatch",
  "name": "StudyInfo_BotDispatch",
  "desc": "Dispatch model for StudyInfo_BotDispatch",
  "culture": "nl-nl",
  "intents": [
    {
      "name": "l_HoGentGeneral"
    },
    {
      "name": "l_Training Courses"
    }
  ],
  "entities": [],
  "composites": [],
  "closedLists": [],
  "patternAnyEntities": [],
  "regex_entities": [],
  "prebuiltEntities": [],
  "model_features": [],
  "regex_features": [],
  "patterns": [],
  "utterances": [
    {
      "text": "hoeveel bedraagt het inschrijvingsgeld",
      "intent": "l_HoGentGeneral",
      "entities": []
    },
    {
      "text": "hoeveel is het inschrijvingsgeld",
      "intent": "l_HoGentGeneral",
      "entities": []
    },
    {
      "text": "wat zijn de studiekosten",
      "intent": "l_HoGentGeneral",
      "entities": []
    },
    {
      "text": "hoeveel moet ik voor de opleiding betalen",
      "intent": "l_HoGentGeneral",
      "entities": []
    },
    {
      "text": "hoeveel moet ik betalen",
      "intent": "l_HoGentGeneral",
      "entities": []
    },
    {
      "text": "studiekosten",
      "intent": "l_HoGentGeneral",
      "entities": []
    },
    {
      "text": "hoeveel kost de opleiding",
      "intent": "l_HoGentGeneral",
      "entities": []
    },
    {
      "text": "hoeveel ga ik moeten studeren voor wiskunde",
      "intent": "l_Training Courses",
      "entities": []
    },
    {
      "text": "wat is het gewicht van analyse1",
      "intent": "l_Training Courses",
      "entities": []
    },
    {
      "text": "hoelang moet ik studeren voor analyse 1",
      "intent": "l_Training Courses",
      "entities": []
    },
    {
      "text": "hoeveel tijd moet ik studeren voor wiskunde",
      "intent": "l_Training Courses",
      "entities": []
    },
    {
      "text": "hoeveel studiepunten heeft het vak analyse i",
      "intent": "l_Training Courses",
      "entities": []
    },
    {
      "text": "wat is de studieomvang van probleemoplossend denken 1",
      "intent": "l_Training Courses",
      "entities": []
    },
    {
      "text": "welke docent krijg ik voor het vak wiskunde",
      "intent": "l_Training Courses",
      "entities": []
    },
    {
      "text": "hoeveel uren heb ik nodig om het analyse1 te begrijpen",
      "intent": "l_Training Courses",
      "entities": []
    },
    {
      "text": "gewicht wiskunde",
      "intent": "l_Training Courses",
      "entities": []
    },
    {
      "text": "welke leerkracht geeft het vak wiskunde",
      "intent": "l_Training Courses",
      "entities": []
    },
    {
      "text": "kan ik wiskunde studeren op 10 uur",
      "intent": "l_Training Courses",
      "entities": []
    },
    {
      "text": "studiepunten computerarchitectuur",
      "intent": "l_Training Courses",
      "entities": []
    },
    {
      "text": "wie geeft het vak wiskunde",
      "intent": "l_Training Courses",
      "entities": []
    },
    {
      "text": "gewicht analyse 1",
      "intent": "l_Training Courses",
      "entities": []
    },
    {
      "text": "hoeveel tijd moet ik voorzien voor wiskunde",
      "intent": "l_Training Courses",
      "entities": []
    },
    {
      "text": "docent wiskunde",
      "intent": "l_Training Courses",
      "entities": []
    }
  ],
  "settings": []
}
